[
  {
    "area": "Clementi",
    "hdb_price_range": "SGD 366K - 715K",
    "pros": [
      "Excellent location near NUS and one-north business hub",
      "Strong connectivity via MRT and expressways (AYE, PIE)",
      "Mature town with established schools and amenities"
    ],
    "cons": [
      "Flats are generally older and high in demand",
      "Limited space for new BTO projects"
    ],
    "nearby_amenities": [
      "Clementi Mall",
      "Clementi Sports Hall",
      "West Coast Park"
    ]
  },
  {
    "area": "Serangoon",
    "hdb_price_range": "SGD 408K - 679K",
    "pros": [
      "Centrally located with easy access to major expressways",
      "Popular for its food and shopping options (NEX Mall)",
      "Quiet and established residential neighbourhoods"
    ],
    "cons": [
      "Limited number of HDB flats",
      "Higher prices due to central location"
    ],
    "nearby_amenities": [
      "NEX Mall",
      "Serangoon Gardens Food Centre",
      "Serangoon Community Park"
    ]
  },
  {
    "area": "Tampines",
    "hdb_price_range": "SGD 430K - 660K",
    "pros": [
      "Mature town with full amenities",
      "Good MRT and bus connectivity",
      "Close to Changi Airport"
    ],
    "cons": [
      "Can be crowded during peak hours",
      "Far from central business district"
    ],
    "nearby_amenities": [
      "Our Tampines Hub",
      "Tampines Eco Green",
      "Tampines Mall"
    ]
  },
  {
    "area": "Woodlands",
    "hdb_price_range": "SGD 362K - 560K",
    "pros": [
      "Affordable HDB options",
      "Family-friendly environment",
      "Close to Malaysia via Causeway"
    ],
    "cons": [
      "Far from city centre",
      "Traffic jams near Causeway"
    ],
    "nearby_amenities": [
      "Causeway Point",
      "Woodlands Waterfront Park",
      "Republic Polytechnic Sports Complex"
    ]
  },
  {
    "area": "Punggol",
    "hdb_price_range": "SGD 448K - 620K",
    "pros": [
      "Modern new town",
      "Scenic waterfront lifestyle",
      "Family-oriented with parks and schools"
    ],
    "cons": [
      "Still developing, fewer established amenities",
      "Longer MRT travel time to CBD"
    ],
    "nearby_amenities": [
      "Waterway Point",
      "Punggol Waterway Park",
      "One Punggol Hub"
    ]
  },
  {
    "area": "Toa Payoh",
    "hdb_price_range": "SGD 320K - 776K",
    "pros": [
      "One of the first HDB towns with strong heritage",
      "Central location with good transport links",
      "Plenty of hawker centres and amenities"
    ],
    "cons": [
      "Older flats with smaller layouts",
      "Can be noisy and crowded"
    ],
    "nearby_amenities": [
      "Toa Payoh Central Community Club",
      "Toa Payoh Town Park",
      "Toa Payoh Swimming Complex"
    ]
  },
  {
    "area": "Yishun",
    "hdb_price_range": "SGD 343K - 530K",
    "pros": [
      "Affordable compared to other areas",
      "Plenty of neighbourhood amenities",
      "Close to nature parks like Lower Seletar Reservoir"
    ],
    "cons": [
      "Far from city centre",
      "Reputation for being less desirable in the past"
    ],
    "nearby_amenities": [
      "Northpoint City",
      "Yishun Park Hawker Centre",
      "Lower Seletar Reservoir Park"
    ]
  },
  {
    "area": "Pasir Ris",
    "hdb_price_range": "SGD 470K - 668K",
    "pros": [
      "Coastal town with access to beaches",
      "Relaxed and family-friendly vibe",
      "Close to Changi Airport"
    ],
    "cons": [
      "Far from city centre",
      "Limited nightlife and entertainment options"
    ],
    "nearby_amenities": [
      "Downtown East",
      "Pasir Ris Park",
      "Pasir Ris Sports Centre"
    ]
  },
  {
    "area": "Queenstown",
    "hdb_price_range": "SGD 375K - 835K",
    "pros": [
      "City-fringe location close to CBD and Orchard",
      "Rich history and heritage sites",
      "Part of Greater Southern Waterfront redevelopment"
    ],
    "cons": [
      "Older flats with higher prices",
      "Limited new BTO projects"
    ],
    "nearby_amenities": [
      "Queensway Shopping Centre",
      "Alexandra Hospital Park",
      "Queenstown Sports Complex"
    ]
  },
  {
    "area": "Ang Mo Kio",
    "hdb_price_range": "SGD 328K - 570K",
    "pros": [
      "Mature estate with strong amenities",
      "Good transport links with upcoming MRT lines",
      "Plenty of food options and neighbourhood malls"
    ],
    "cons": [
      "Flats are older compared to newer estates",
      "Crowded during peak hours"
    ],
    "nearby_amenities": [
      "AMK Hub",
      "Bishan-Ang Mo Kio Park",
      "Ang Mo Kio Swimming Complex"
    ]
  },
  {
    "area": "Jurong East",
    "hdb_price_range": "SGD 352K - 565K",
    "pros": [
      "Upcoming second CBD with new developments in Jurong Lake District",
      "Strong retail presence (JEM, Westgate, IMM)",
      "Excellent connectivity via multiple MRT lines"
    ],
    "cons": [
      "Ongoing construction may cause congestion",
      "Rising property prices due to redevelopment plans"
    ],
    "nearby_amenities": [
      "JEM",
      "Westgate",
      "Jurong Lake Gardens"
    ]
  },
  {
    "area": "Jurong West",
    "hdb_price_range": "SGD 360K - 545K",
    "pros": [
      "Affordable housing options",
      "Close proximity to Jurong Innovation District and NTU",
      "Green surroundings with parks and lakes nearby"
    ],
    "cons": [
      "Far from central Singapore",
      "Limited entertainment and dining venues"
    ],
    "nearby_amenities": [
      "Jurong Point",
      "NTU Sports Centre",
      "Lakeside Garden"
    ]
  }
]